{
  "country": {
    "code": "CN",
    "name_fr": "Chine"
  },
  "mission": {
    "mission_id": "CN-S1-003",
    "mission_title": "OPÉRATION DRAGON SILENCIEUX",
    "phase": "INFRASTRUCTURE_NODE",
    "is_free": true,
    "detective": "Jasper Valcourt",
    "intro": "Pékin. Ciel gris. Silence dense.\n\nAprès la Suisse et les États-Unis,\nJasper comprend une chose :\n\nLes flux doivent circuler.\nLe rythme doit être régulé.\n\nMais qui construit les routes ?\n\n2013.\nLancement d'un projet reliant l'Asie, l'Europe et l'Afrique.\n\nDes ports.\nDes chemins de fer.\nDes câbles.\n\nUne nouvelle monnaie numérique.\n\nLa puissance ne se montre pas toujours.\nElle s'installe.\n\nSi Washington règle la cadence,\nPékin construit le réseau.\n\nVotre mission :\nComprendre comment l'infrastructure devient une arme géostratégique."
  },
  "quiz_rules": {
    "total_questions": 10,
    "draw_per_run": 6,
    "distribution": {
      "A": 4,
      "B": 1,
      "C": 1
    },
    "max_mistakes": 1
  },
  "question_bank": [
    {
      "id": "CN_Q1",
      "type": "A",
      "question": "Quelle est la capitale de la Chine ?",
      "choices": ["Shanghai", "Hong Kong", "Pékin", "Shenzhen"],
      "answer_index": 2
    },
    {
      "id": "CN_Q2",
      "type": "A",
      "question": "En quelle année a été lancée l'initiative des Nouvelles Routes de la Soie (Belt and Road Initiative) ?",
      "choices": ["2008", "2010", "2013", "2016"],
      "answer_index": 2
    },
    {
      "id": "CN_Q3",
      "type": "A",
      "question": "Quelle ville chinoise est l'un des plus grands hubs financiers du pays ?",
      "choices": ["Xi'an", "Shanghai", "Chengdu", "Harbin"],
      "answer_index": 1
    },
    {
      "id": "CN_Q4",
      "type": "A",
      "question": "Quel océan borde la côte est de la Chine ?",
      "choices": ["Océan Indien", "Océan Pacifique", "Océan Atlantique", "Océan Arctique"],
      "answer_index": 1
    },
    {
      "id": "CN_Q5",
      "type": "A",
      "question": "Quelle monnaie officielle est utilisée en Chine ?",
      "choices": ["Yen", "Won", "Renminbi (Yuan)", "Baht"],
      "answer_index": 2
    },
    {
      "id": "CN_Q6",
      "type": "A",
      "question": "Quel est le nom de la monnaie numérique développée par la Banque populaire de Chine ?",
      "choices": ["CryptoYuan", "e-CNY (yuan numérique)", "DragonCoin", "Digital Silk"],
      "answer_index": 1
    },
    {
      "id": "CN_Q7",
      "type": "B",
      "question": "Pourquoi les infrastructures (ports, chemins de fer, câbles) sont-elles stratégiques ?",
      "choices": [
        "Elles attirent uniquement le tourisme",
        "Elles permettent d'influencer les flux commerciaux et politiques",
        "Elles remplacent les gouvernements",
        "Elles servent uniquement au transport militaire"
      ],
      "answer_index": 1
    },
    {
      "id": "CN_Q8",
      "type": "B",
      "question": "Quel est l'objectif géopolitique majeur de la Belt and Road Initiative ?",
      "choices": [
        "Isoler la Chine",
        "Créer un réseau mondial d'interdépendance économique",
        "Supprimer les frontières",
        "Fermer les marchés asiatiques"
      ],
      "answer_index": 1
    },
    {
      "id": "CN_Q9",
      "type": "C",
      "question": "Dans la logique du système mondial, que représente le réseau d'infrastructures chinois ?",
      "choices": [
        "Un simple projet de construction",
        "Un outil culturel",
        "Un levier d'influence à long terme",
        "Un mécanisme temporaire"
      ],
      "answer_index": 2,
      "narrative_unlock": "Celui qui construit les routes décide où passent les flux."
    },
    {
      "id": "CN_Q10",
      "type": "C",
      "question": "Quel lien relie les Routes de la Soie, les ports internationaux et le yuan numérique ?",
      "choices": [
        "La volonté d'isolement",
        "Le contrôle discret des échanges",
        "Une domination militaire directe",
        "Un hasard économique"
      ],
      "answer_index": 1,
      "narrative_unlock": "Le réseau précède le pouvoir."
    }
  ],
  "fragment_reward": {
    "id": "FRAG-CN-003",
    "name": "Fragment Dragon Silencieux",
    "concept": "NŒUD_INFRASTRUCTURE",
    "unlocked_message": "Celui qui construit les routes décide où passent les flux."
  }
}
